annotator/__init__.py
annotator/example.py
annotator/frontend/dist/index.html
annotator/frontend/dist/assets/browser-BCZA1zVj.js
annotator/frontend/dist/assets/browser-BGtEBiJZ.js
annotator/frontend/dist/assets/index-DrBqgfis.css
annotator/frontend/dist/assets/index-GJc9Ey7a.js
annotator/frontend/dist/assets/index-O_eoPyqU.js
streamlit_pdf_annotator-0.0.1.dist-info/LICENSE
streamlit_pdf_annotator-0.0.1.dist-info/METADATA
streamlit_pdf_annotator-0.0.1.dist-info/WHEEL
streamlit_pdf_annotator-0.0.1.dist-info/top_level.txt
streamlit_pdf_annotator-0.0.1.dist-info/RECORD
