Metadata-Version: 2.1
Name: streamlit-pdf-annotator
Version: 0.0.1
Summary: Streamlit component that allows you to annotate PDFs
Home-page: UNKNOWN
Author: UnihackErasmusTeam
Author-email: 4ndr3s@duck.com
License: UNKNOWN
Platform: UNKNOWN
Requires-Python: >=3.7
License-File: LICENSE
Requires-Dist: streamlit (>=0.63)
